vs2dpy/__init__.py
vs2dpy/model.py
vs2dpy/read.py
vs2dpy/utils.py
vs2dpy-0.3.0.dist-info/LICENSE
vs2dpy-0.3.0.dist-info/METADATA
vs2dpy-0.3.0.dist-info/WHEEL
vs2dpy-0.3.0.dist-info/top_level.txt
vs2dpy-0.3.0.dist-info/RECORD
