Metadata-Version: 2.1
Name: vs2dpy
Version: 0.3.0
Summary: Python package to create VS2DRTI unsaturated zone models
Author: Martin Vonk
License: MIT License
Classifier: Programming Language :: Python :: 3
Classifier: License :: OSI Approved :: MIT License
Classifier: Operating System :: OS Independent
Requires-Python: >=3.7
License-File: LICENSE
Requires-Dist: numpy
Requires-Dist: matplotlib
Requires-Dist: pandas
